MANIFEST.in
Readme.md
setup.py
metrics/__init__.py
metrics/cdo.py
metrics/crpss.py
metrics/crpss_zonal.py
metrics/filehandler.py
metrics/findFiles.py
metrics/findFilesAbstract.py
metrics/findFilesCustom.py
metrics/findFilesCustomSeason.py
metrics/findFilesSeason.py
metrics/metricAbstract.py
metrics/msss.py
metrics/msssBootstrap.py
metrics/murcss.py
metrics/murcss_config.py
metrics/nondeamonpool.py
metrics/plotter.py
metrics/plotter_test.py
metrics/significance2.py
metrics/taylorplot.py
metrics/tool_abstract.py
murcss.egg-info/PKG-INFO
murcss.egg-info/SOURCES.txt
murcss.egg-info/dependency_links.txt
murcss.egg-info/entry_points.txt
murcss.egg-info/requires.txt
murcss.egg-info/top_level.txt