Metadata-Version: 1.0
Name: murcss
Version: 1.6.1
Summary: MurCSS: A Tool for Standardized Evaluation of Decadal Hindcast Systems
Home-page: https://github.com/illing2005/murcss
Author: Sebastian Illing
Author-email: sebastian.illing@met.fu-berlin.de
License: GPLv3
Keywords: Decadal prediction,skill score,MiKlip,MSESS,CRPSS,model evaluation,verification
Platform: UNKNOWN
Classifier: Development Status :: 5 - Production/Stable
Classifier: Programming Language :: Python :: 2.7
